dory/__init__.py
dory/py.typed
dory/common/__init__.py
dory/common/exceptions.py
dory/common/types.py
dory/embeddings/__init__.py
dory/embeddings/builders.py
dory/embeddings/config.py
dory/embeddings/service.py
dory/embeddings/adapters/__init__.py
dory/embeddings/adapters/base.py
dory/embeddings/adapters/mem0.py
dory/embeddings/adapters/types.py
dory/embeddings/models/__init__.py
dory/messages/__init__.py
dory/messages/config.py
dory/messages/service.py
dory/messages/adapters/__init__.py
dory/messages/adapters/base.py
dory/messages/adapters/in_memory.py
dory/messages/adapters/mongo.py
dory/messages/adapters/utils.py
dory/messages/models/__init__.py
dory/messages/models/conversation.py
dory/messages/models/message.py
dory/users_summaries/__init__.py
dory/users_summaries/agent.py
dory/users_summaries/config.py
dory/users_summaries/service.py
dory/users_summaries/adapters/__init__.py
dory/users_summaries/adapters/base.py
dory/users_summaries/adapters/in_memory.py
dory/users_summaries/adapters/mongo.py
dory/users_summaries/models/__init__.py
dory/users_summaries/models/action.py
dory/users_summaries/models/users_summaries.py
dory/users_summaries/prompt_modules/__init__.py
dory/users_summaries/prompt_modules/types.py
dory/users_summaries/prompt_modules/user_summary_generation.py
dory_ai-0.2.5.dist-info/METADATA
dory_ai-0.2.5.dist-info/WHEEL
dory_ai-0.2.5.dist-info/licenses/LICENSE
dory_ai-0.2.5.dist-info/RECORD
