Metadata-Version: 2.4
Name: dory-ai
Version: 0.2.5
Summary: A library for managing conversation history in AI-powered applications for reusability across projects.
Author-email: Kopiloto Team <kopiloto@kavak.com>
License: MIT
License-File: LICENSE
Keywords: ai,conversation,messages,mongodb
Requires-Python: >=3.12
Requires-Dist: httpx>=0.27.0
Requires-Dist: mem0ai>=0.0.20
Requires-Dist: mongoengine-plus-pymongo-4>=1.2.1
Requires-Dist: pydantic-ai>=1.0.18
Requires-Dist: pydantic>=2.5.0
Provides-Extra: linting
Requires-Dist: mypy; extra == 'linting'
Requires-Dist: ruff; extra == 'linting'
Requires-Dist: types-requests; extra == 'linting'
